README.md
setup.py
metascholar/__init__.py
metascholar/download.py
metascholar/log_process.py
metascholar/metadata.py
metascholar.egg-info/PKG-INFO
metascholar.egg-info/SOURCES.txt
metascholar.egg-info/dependency_links.txt
metascholar.egg-info/requires.txt
metascholar.egg-info/top_level.txt